firmeapi/__init__.py
firmeapi/client.py
firmeapi/exceptions.py
firmeapi/py.typed
firmeapi/types.py
firmeapi-1.0.0.dist-info/METADATA
firmeapi-1.0.0.dist-info/WHEEL
firmeapi-1.0.0.dist-info/RECORD
