Metadata-Version: 2.4
Name: firmeapi
Version: 1.0.0
Summary: Official Python SDK for FirmeAPI.ro - Romanian company data API
Project-URL: Homepage, https://www.firmeapi.ro
Project-URL: Documentation, https://www.firmeapi.ro/docs
Project-URL: Repository, https://github.com/aicloudro/firmeapi-python
Project-URL: Issues, https://github.com/aicloudro/firmeapi-python/issues
Author-email: "FirmeAPI.ro" <contact@firmeapi.ro>
License-Expression: MIT
Keywords: anaf,api,business,company,cui,firmeapi,romania,sdk
Classifier: Development Status :: 5 - Production/Stable
Classifier: Intended Audience :: Developers
Classifier: License :: OSI Approved :: MIT License
Classifier: Operating System :: OS Independent
Classifier: Programming Language :: Python :: 3
Classifier: Programming Language :: Python :: 3.9
Classifier: Programming Language :: Python :: 3.10
Classifier: Programming Language :: Python :: 3.11
Classifier: Programming Language :: Python :: 3.12
Classifier: Topic :: Software Development :: Libraries :: Python Modules
Classifier: Typing :: Typed
Requires-Python: >=3.9
Requires-Dist: httpx>=0.25.0
Provides-Extra: dev
Requires-Dist: mypy>=1.0.0; extra == 'dev'
Requires-Dist: pytest-asyncio>=0.21.0; extra == 'dev'
Requires-Dist: pytest>=7.0.0; extra == 'dev'
Requires-Dist: ruff>=0.1.0; extra == 'dev'
